novabot_plugin_word_bank/__init__.py
novabot_plugin_word_bank/data_source.py
novabot_plugin_word_bank/models.py
novabot_plugin_word_bank/util.py
novabot_plugin_word_bank/word_entry.py
novabot_plugin_word_bank-0.1.1.dist-info/LICENSE
novabot_plugin_word_bank-0.1.1.dist-info/WHEEL
novabot_plugin_word_bank-0.1.1.dist-info/METADATA
novabot_plugin_word_bank-0.1.1.dist-info/RECORD
