Metadata-Version: 2.1
Name: novabot-plugin-word-bank
Version: 0.1.1
Summary: Nova-Bot 使用的无数据库的问答插件
Author: NovaNo1r
Author-email: mail@novanoir.dev
Requires-Python: >=3.10,<4.0
Classifier: Programming Language :: Python :: 3
Classifier: Programming Language :: Python :: 3.10
Requires-Dist: aiofiles (>=0.8.0,<0.9.0)
Requires-Dist: httpx (>=0.23.0,<0.24.0)
